{
	"backtrace" : 4,
	"backtraceGraph" : 
	{
		"commands" : 
		[
			"add_custom_target",
			"include",
			"generate_messages",
			"add_dependencies"
		],
		"files" : 
		[
			"/home/park/catkin_ws/build/gcamp_ros_basic/cpp_service_tutorial/cmake/cpp_service_tutorial-genmsg.cmake",
			"/opt/ros/noetic/share/genmsg/cmake/genmsg-extras.cmake",
			"gcamp_ros_basic/cpp_service_tutorial/CMakeLists.txt"
		],
		"nodes" : 
		[
			{
				"file" : 2
			},
			{
				"command" : 2,
				"file" : 2,
				"line" : 71,
				"parent" : 0
			},
			{
				"command" : 1,
				"file" : 1,
				"line" : 307,
				"parent" : 1
			},
			{
				"file" : 0,
				"parent" : 2
			},
			{
				"command" : 0,
				"file" : 0,
				"line" : 14,
				"parent" : 3
			},
			{
				"command" : 3,
				"file" : 0,
				"line" : 148,
				"parent" : 3
			},
			{
				"command" : 3,
				"file" : 0,
				"line" : 49,
				"parent" : 3
			},
			{
				"command" : 3,
				"file" : 0,
				"line" : 82,
				"parent" : 3
			},
			{
				"command" : 3,
				"file" : 0,
				"line" : 115,
				"parent" : 3
			},
			{
				"command" : 3,
				"file" : 0,
				"line" : 181,
				"parent" : 3
			}
		]
	},
	"dependencies" : 
	[
		{
			"backtrace" : 5,
			"id" : "cpp_service_tutorial_generate_messages_nodejs::@c817220a3f54490a8a70"
		},
		{
			"backtrace" : 6,
			"id" : "cpp_service_tutorial_generate_messages_cpp::@c817220a3f54490a8a70"
		},
		{
			"backtrace" : 7,
			"id" : "cpp_service_tutorial_generate_messages_eus::@c817220a3f54490a8a70"
		},
		{
			"backtrace" : 8,
			"id" : "cpp_service_tutorial_generate_messages_lisp::@c817220a3f54490a8a70"
		},
		{
			"backtrace" : 9,
			"id" : "cpp_service_tutorial_generate_messages_py::@c817220a3f54490a8a70"
		}
	],
	"id" : "cpp_service_tutorial_generate_messages::@c817220a3f54490a8a70",
	"name" : "cpp_service_tutorial_generate_messages",
	"paths" : 
	{
		"build" : "gcamp_ros_basic/cpp_service_tutorial",
		"source" : "gcamp_ros_basic/cpp_service_tutorial"
	},
	"sources" : [],
	"type" : "UTILITY"
}
